mkdocstrings_extensions_simple_config_builder/__about__.py
mkdocstrings_extensions_simple_config_builder/__init__.py
mkdocstrings_extensions_simple_config_builder/simple_config_builder_extension.py
mkdocstrings_extensions_simple_config_builder-0.3.0.dist-info/METADATA
mkdocstrings_extensions_simple_config_builder-0.3.0.dist-info/WHEEL
mkdocstrings_extensions_simple_config_builder-0.3.0.dist-info/entry_points.txt
mkdocstrings_extensions_simple_config_builder-0.3.0.dist-info/licenses/LICENSE.txt
mkdocstrings_extensions_simple_config_builder-0.3.0.dist-info/RECORD
