Metadata-Version: 2.4
Name: mkdocstrings-extensions-simple-config-builder
Version: 0.3.0
Project-URL: Documentation, https://github.com/jogehl/mkdocstrings-extensions-simple-config-builder#readme
Project-URL: Issues, https://github.com/jogehl/mkdocstrings-extensions-simple-config-builder/issues
Project-URL: Source, https://github.com/jogehln/mkdocstrings-extensions-simple-config-builder
Author-email: jogehl <joshuagehlen@hotmail.com>
License-Expression: MIT
License-File: LICENSE.txt
Classifier: Development Status :: 4 - Beta
Classifier: Programming Language :: Python
Classifier: Programming Language :: Python :: 3.8
Classifier: Programming Language :: Python :: 3.9
Classifier: Programming Language :: Python :: 3.10
Classifier: Programming Language :: Python :: 3.11
Classifier: Programming Language :: Python :: 3.12
Classifier: Programming Language :: Python :: Implementation :: CPython
Classifier: Programming Language :: Python :: Implementation :: PyPy
Requires-Python: >=3.11
Requires-Dist: griffe
